estela_requests/__init__.py
estela_requests/config.py
estela_requests/default_settings.py
estela_requests/estela_http.py
estela_requests/estela_hub.py
estela_requests/exceptions.py
estela_requests/request_interfaces.py
estela_requests/settings_remote.py
estela_requests/utils.py
estela_requests/item_pipeline/__init__.py
estela_requests/item_pipeline/default.py
estela_requests/item_pipeline/exporter.py
estela_requests/item_pipeline/manager.py
estela_requests/log_helpers/__init__.py
estela_requests/log_helpers/handlers.py
estela_requests/middlewares/__init__.py
estela_requests/middlewares/interface.py
estela_requests/middlewares/manager.py
estela_requests/middlewares/requests_history.py
estela_requests/middlewares/spider_status.py
estela_requests/middlewares/stats.py
estela_requests-1.0.1.dist-info/METADATA
estela_requests-1.0.1.dist-info/WHEEL
estela_requests-1.0.1.dist-info/top_level.txt
estela_requests-1.0.1.dist-info/RECORD
