Metadata-Version: 2.1
Name: estela-requests
Version: 1.0.1
Summary: estela_requests is a request wrapper for estela.
Home-page: https://github.com/bitmakerla/estela-requests
License: UNKNOWN
Platform: UNKNOWN
Classifier: Development Status :: 2 - Pre-Alpha
Classifier: Intended Audience :: Developers
Classifier: License :: OSI Approved :: MIT License
Classifier: Operating System :: OS Independent
Classifier: Programming Language :: Python :: 3
Classifier: Programming Language :: Python :: 3.7
Classifier: Programming Language :: Python :: 3.8
Classifier: Programming Language :: Python :: 3.9
Classifier: Topic :: Software Development :: Libraries :: Python Modules
Requires-Python: >=3.7
Requires-Dist: estela (>=0.0.2)
Requires-Dist: requests (>=2.0.0)
Requires-Dist: estela-queue-adapter
Requires-Dist: dynaconf
